new_openapi/_hooks/registration.py
speakeasy/new_openapi/__init__.py
speakeasy/new_openapi/_version.py
speakeasy/new_openapi/basesdk.py
speakeasy/new_openapi/httpclient.py
speakeasy/new_openapi/py.typed
speakeasy/new_openapi/sdk.py
speakeasy/new_openapi/sdkconfiguration.py
speakeasy/new_openapi/tag1.py
speakeasy/new_openapi/tag2.py
speakeasy/new_openapi/tag3.py
speakeasy/new_openapi/testgroup.py
speakeasy/new_openapi/_hooks/__init__.py
speakeasy/new_openapi/_hooks/clientcredentials.py
speakeasy/new_openapi/_hooks/registration.py
speakeasy/new_openapi/_hooks/sdkhooks.py
speakeasy/new_openapi/_hooks/types.py
speakeasy/new_openapi/models/__init__.py
speakeasy/new_openapi/models/_operation_with_leading_and_trailing_underscores_op.py
speakeasy/new_openapi/models/badrequestresponse_error.py
speakeasy/new_openapi/models/baseuser.py
speakeasy/new_openapi/models/binaryandstringuploadop.py
speakeasy/new_openapi/models/chatop.py
speakeasy/new_openapi/models/circularunion.py
speakeasy/new_openapi/models/color.py
speakeasy/new_openapi/models/deleteuserop.py
speakeasy/new_openapi/models/deprecated1op.py
speakeasy/new_openapi/models/disriminatedunionwithonemember.py
speakeasy/new_openapi/models/enum.py
speakeasy/new_openapi/models/errors_error.py
speakeasy/new_openapi/models/errortype1.py
speakeasy/new_openapi/models/errortype2.py
speakeasy/new_openapi/models/exhaustiveobject.py
speakeasy/new_openapi/models/file.py
speakeasy/new_openapi/models/gender.py
speakeasy/new_openapi/models/geterrorinunionop.py
speakeasy/new_openapi/models/getfullyflattenedrequestop.py
speakeasy/new_openapi/models/getpolymorphismop.py
speakeasy/new_openapi/models/getrequestbodyflattenedawayop.py
speakeasy/new_openapi/models/getunionerrorsop.py
speakeasy/new_openapi/models/getuserop.py
speakeasy/new_openapi/models/listtest1op.py
speakeasy/new_openapi/models/loginop.py
speakeasy/new_openapi/models/metadata.py
speakeasy/new_openapi/models/no_response_error.py
closedapi_test_pythonv2_4-0.0.1.dist-info/METADATA
closedapi_test_pythonv2_4-0.0.1.dist-info/WHEEL
closedapi_test_pythonv2_4-0.0.1.dist-info/top_level.txt
closedapi_test_pythonv2_4-0.0.1.dist-info/RECORD
